clipbit/__init__.py
clipbit/__main__.py
clipbit/clipbit.py
clipbit/script.py
clipbit/text_summary.py
clipbit-1.0.0.dist-info/METADATA
clipbit-1.0.0.dist-info/WHEEL
clipbit-1.0.0.dist-info/dependency_links.txt
clipbit-1.0.0.dist-info/entry_points.txt
clipbit-1.0.0.dist-info/top_level.txt
clipbit-1.0.0.dist-info/RECORD
