Metadata-Version: 2.1
Name: clipbit
Version: 1.0.0
Summary: Generate concise meaningful summaries YouTube videos
Home-page: https://github.com/MLH-Fellowship/ClipBit
Author: Sarthak Khattar <sarthakoct@gmail.com>, Miguel Guardia <guardia@ualberta.ca>, Kimaru Thagana <thagana44@gmail.com>
License: MIT
Download-URL: https://github.com/MLH-Fellowship/ClipBit/archive/v1.0.tar.gz
Keywords: nlp,youtube,cli,captions
Platform: UNKNOWN
Classifier: Development Status :: 3 - Alpha
Classifier: Intended Audience :: Developers
Classifier: Topic :: Software Development :: Build Tools
Classifier: License :: OSI Approved :: MIT License
Classifier: Programming Language :: Python :: 3
Classifier: Programming Language :: Python :: 3.4
Classifier: Programming Language :: Python :: 3.5
Classifier: Programming Language :: Python :: 3.6
Requires-Dist: torch (==1.7.1+cpu)
Requires-Dist: torchvision (==0.8.2+cpu)
Requires-Dist: torchaudio (==0.7.2)
Requires-Dist: pytube (==10.4.1)
Requires-Dist: pysrt (==1.1.2)
Requires-Dist: click (==7.1.2)
Requires-Dist: transformers (==4.2.2)
Requires-Dist: sentencepiece (==0.1.95)
Requires-Dist: colorama (==0.4.4)
Requires-Dist: rich (==9.10.0)
